mmv_h4tracks/__init__.py
mmv_h4tracks/_analysis.py
mmv_h4tracks/_assistant.py
mmv_h4tracks/_evaluation.py
mmv_h4tracks/_grabber.py
mmv_h4tracks/_logger.py
mmv_h4tracks/_processing.py
mmv_h4tracks/_reader.py
mmv_h4tracks/_segmentation.py
mmv_h4tracks/_selector.py
mmv_h4tracks/_tracking.py
mmv_h4tracks/_widget.py
mmv_h4tracks/_writer.py
mmv_h4tracks/add_models.py
mmv_h4tracks/custom_models.json
mmv_h4tracks/napari.yaml
mmv_h4tracks/_tests/__init__.py
mmv_h4tracks/_tests/test_evaluation.py
mmv_h4tracks/_tests/test_processing.py
mmv_h4tracks/_tests/test_segmentation.py
mmv_h4tracks/_tests/test_tracking.py
mmv_h4tracks/_tests/test_widget.py
mmv_h4tracks/models/Neutrophil_granulocytes
mmv_h4tracks/models/custom_models/.gitkeep
mmv_h4tracks/ressources/celltracking_logo.jpg
mmv_h4tracks-1.2.0.dist-info/LICENSE
mmv_h4tracks-1.2.0.dist-info/METADATA
mmv_h4tracks-1.2.0.dist-info/WHEEL
mmv_h4tracks-1.2.0.dist-info/entry_points.txt
mmv_h4tracks-1.2.0.dist-info/top_level.txt
mmv_h4tracks-1.2.0.dist-info/RECORD
