Metadata-Version: 2.2
Name: mmv_h4tracks
Version: 1.2.0
Summary: Human in the loop 2d cell migration analysis
Author-email: Lennart Kowitz <lennart.kowitz@isas.de>, Justin Sonneck <justin.sonneck@isas.de>
License: 
Project-URL: Homepage, https://github.com/MMV-Lab/mmv_h4tracks
Project-URL: Bug Tracker, https://github.com/MMV-Lab/mmv_h4tracks/issues
Project-URL: Documentation, https://github.com/MMV-Lab/mmv_h4tracks#README.md
Project-URL: Source Code, https://github.com/MMV-Lab/mmv_h4tracks
Project-URL: User Support, https://github.com/MMV-Lab/mmv_h4tracks/issues
Classifier: Development Status :: 5 - Production/Stable
Classifier: Intended Audience :: Science/Research
Classifier: Framework :: napari
Classifier: Topic :: Scientific/Engineering :: Image Processing
Classifier: Programming Language :: Python
Classifier: Programming Language :: Python :: 3
Classifier: Programming Language :: Python :: 3.9
Classifier: Programming Language :: Python :: 3.10
Classifier: Programming Language :: Python :: 3.11
Classifier: Programming Language :: Python :: 3.12
Classifier: Operating System :: OS Independent
Classifier: License :: OSI Approved :: BSD License
Requires-Python: >=3.9
License-File: LICENSE
Requires-Dist: numpy
Requires-Dist: npe2
Requires-Dist: napari-plugin-engine>=0.1.4
Requires-Dist: napari
Requires-Dist: zarr
Requires-Dist: cellpose==2.1.0
Requires-Dist: matplotlib
Requires-Dist: aicsimageio
Requires-Dist: scipy>=1.11.0
